aiopg/__init__.py
aiopg/connection.py
aiopg/log.py
aiopg/pool.py
aiopg/py.typed
aiopg/utils.py
aiopg/sa/__init__.py
aiopg/sa/connection.py
aiopg/sa/engine.py
aiopg/sa/exc.py
aiopg/sa/result.py
aiopg/sa/transaction.py
aiopg/sa/utils.py
aiopg-1.4.0.dist-info/LICENSE
aiopg-1.4.0.dist-info/METADATA
aiopg-1.4.0.dist-info/WHEEL
aiopg-1.4.0.dist-info/top_level.txt
aiopg-1.4.0.dist-info/RECORD
