Metadata-Version: 2.1
Name: aiopg
Version: 1.4.0
Summary: Postgres integration with asyncio.
Home-page: https://aiopg.readthedocs.io
Author: Andrew Svetlov
Author-email: andrew.svetlov@gmail.com
Maintainer: Andrew Svetlov <andrew.svetlov@gmail.com>, Alexey Firsov <virmir49@gmail.com>, Alexey Popravka <alexey.popravka@horsedevel.com>, Yury Pliner <yury.pliner@gmail.com>
Maintainer-email: virmir49@gmail.com
License: BSD
Download-URL: https://pypi.python.org/pypi/aiopg
Project-URL: Chat: Gitter, https://gitter.im/aio-libs/Lobby
Project-URL: CI: GA, https://github.com/aio-libs/aiopg/actions?query=workflow%3ACI
Project-URL: Coverage: codecov, https://codecov.io/gh/aio-libs/aiopg
Project-URL: Docs: RTD, https://aiopg.readthedocs.io
Project-URL: GitHub: issues, https://github.com/aio-libs/aiopg/issues
Project-URL: GitHub: repo, https://github.com/aio-libs/aiopg
Platform: macOS
Platform: POSIX
Platform: Windows
Classifier: License :: OSI Approved :: BSD License
Classifier: Intended Audience :: Developers
Classifier: Programming Language :: Python :: 3
Classifier: Programming Language :: Python :: 3 :: Only
Classifier: Programming Language :: Python :: 3.7
Classifier: Programming Language :: Python :: 3.8
Classifier: Programming Language :: Python :: 3.9
Classifier: Programming Language :: Python :: 3.10
Classifier: Programming Language :: Python :: 3.11
Classifier: Operating System :: POSIX
Classifier: Operating System :: MacOS :: MacOS X
Classifier: Operating System :: Microsoft :: Windows
Classifier: Environment :: Web Environment
Classifier: Development Status :: 5 - Production/Stable
Classifier: Topic :: Database
Classifier: Topic :: Database :: Front-Ends
Classifier: Framework :: AsyncIO
Requires-Python: >=3.7
Provides-Extra: sa
License-File: LICENSE
